pandasgwas/Association.py
pandasgwas/Browser.py
pandasgwas/Study.py
pandasgwas/Trait.py
pandasgwas/Variant.py
pandasgwas/__init__.py
pandasgwas/client.py
pandasgwas/cytogenetic_bands.csv
pandasgwas/get_associations.py
pandasgwas/get_studies.py
pandasgwas/get_traits.py
pandasgwas/get_variants.py
pandasgwas/set_operation.py
pandasgwas/utility.py
pandasgwas-0.99.11.dist-info/LICENSE
pandasgwas-0.99.11.dist-info/METADATA
pandasgwas-0.99.11.dist-info/WHEEL
pandasgwas-0.99.11.dist-info/top_level.txt
pandasgwas-0.99.11.dist-info/RECORD
