Metadata-Version: 2.1
Name: pandasgwas
Version: 0.99.11
Summary: A Python package for easy retrieval of GWAS Catalog data
Home-page: https://github.com/caotianze/pandasgwas
Author: Cao Tianze
Author-email: hnrcao@qq.com
License: MIT
Project-URL: Bug Tracker, https://github.com/caotianze/pandasgwas/issues
Keywords: gwas,genomics,snp,bioinformatics,pandas
Platform: UNKNOWN
Classifier: Development Status :: 4 - Beta
Classifier: Programming Language :: Python :: 3
Classifier: Programming Language :: Python :: 3.8
Classifier: License :: OSI Approved :: MIT License
Classifier: Operating System :: OS Independent
Requires-Python: >=3.8
License-File: LICENSE
Requires-Dist: pandas (>=1.4.3)
Requires-Dist: requests (>=2.28.1)
Requires-Dist: progressbar2 (>=4.0.0)
